keras_data_format_converter/__init__.py
keras_data_format_converter/converterapi.py
keras_data_format_converter/layers/__init__.py
keras_data_format_converter/layers/confighandlers/__init__.py
keras_data_format_converter/layers/confighandlers/dataformat.py
keras_data_format_converter/layers/layer_utils.py
keras_data_format_converter/modelconverter.py
keras_data_format_converter/utils.py
keras_data_format_converter-0.1.21.dist-info/LICENSE
keras_data_format_converter-0.1.21.dist-info/METADATA
keras_data_format_converter-0.1.21.dist-info/WHEEL
keras_data_format_converter-0.1.21.dist-info/RECORD
