Metadata-Version: 2.1
Name: keras-data-format-converter
Version: 0.1.21
Summary: Generates equal keras models with the desired data format
Author: dorhar
Author-email: doron.harnoy@tensorleap.ai
Requires-Python: >=3.9,<3.11
Classifier: Programming Language :: Python :: 3
Classifier: Programming Language :: Python :: 3.9
Classifier: Programming Language :: Python :: 3.10
Requires-Dist: libclang (==14.0.1)
Requires-Dist: protobuf (>=3.19.6,<=3.20.3)
Requires-Dist: tensorflow (>=2.14,<=2.15) ; platform_machine == "x86_64"
Requires-Dist: tensorflow-addons (>=0.19.0,<0.20.0) ; platform_machine == "x86_64"
Requires-Dist: tensorflow-io-gcs-filesystem (==0.34.0)
Requires-Dist: tensorflow-macos (>=2.14,<=2.15) ; platform_machine == "arm64"
